{
  "repo": "contensis",
  "feeds": [
    {
      "source": "https://www.contensis.com/community/blog",
      "feed_url": "https://www.contensis.com/community/blog",
      "title": "",
      "saved": 0,
      "method": "none"
    },
    {
      "source": "https://www.contensis.com/community/blog/developing-with-the-contensis-image-api",
      "feed_url": "https://www.contensis.com/community/blog/developing-with-the-contensis-image-api",
      "title": "",
      "saved": 0,
      "method": "none"
    },
    {
      "source": "https://www.contensis.com/help-and-docs/apis",
      "feed_url": "https://www.contensis.com/help-and-docs/apis",
      "title": "",
      "saved": 0,
      "method": "none"
    }
  ],
  "post_count": 1,
  "fetched": "2026-06-14T20:42:17Z"
}